subhangpack/__init__.py
subhangpack/info.py
subhangpack/names.py
subhangpack/subhang.py
subhangpack-1.1.0.dist-info/LICENSE
subhangpack-1.1.0.dist-info/METADATA
subhangpack-1.1.0.dist-info/WHEEL
subhangpack-1.1.0.dist-info/entry_points.txt
subhangpack-1.1.0.dist-info/top_level.txt
subhangpack-1.1.0.dist-info/RECORD
