Metadata-Version: 2.1
Name: subhangpack
Version: 1.1.0
Summary: nah you just started
Author: SubhangMokkarala
Author-email: subhangmokkarala@gmail.com
Keywords: python,name,beginner,generator,device,random,fun,subhangpack,subhang,mokkarala,subhangmokkarala
Classifier: Development Status :: 3 - Alpha
Classifier: Intended Audience :: Developers
Classifier: License :: OSI Approved :: MIT License
Classifier: Natural Language :: English
Classifier: Programming Language :: Python :: 3
Classifier: Operating System :: Unix
Classifier: Operating System :: MacOS :: MacOS X
Classifier: Operating System :: Microsoft :: Windows
License-File: LICENSE
Requires-Dist: numpy
